{
  "version": "6",
  "dialect": "sqlite",
  "id": "bf1269c1-d71c-4c7c-9e8a-21ecf1ba6971",
  "prevId": "06d31b14-271c-496f-82a9-4eb891f8bfc7",
  "tables": {
    "admin_session": {
      "name": "admin_session",
      "columns": {
        "id": {
          "name": "id",
          "type": "text",
          "primaryKey": true,
          "notNull": true,
          "autoincrement": false
        },
        "expires_at": {
          "name": "expires_at",
          "type": "integer",
          "primaryKey": false,
          "notNull": true,
          "autoincrement": false
        }
      },
      "indexes": {
        "admin_session_id_idx": {
          "name": "admin_session_id_idx",
          "columns": [
            "id"
          ],
          "isUnique": true
        }
      },
      "foreignKeys": {},
      "compositePrimaryKeys": {},
      "uniqueConstraints": {}
    },
    "analysis_history": {
      "name": "analysis_history",
      "columns": {
        "id": {
          "name": "id",
          "type": "text",
          "primaryKey": true,
          "notNull": true,
          "autoincrement": false
        },
        "project_id": {
          "name": "project_id",
          "type": "text",
          "primaryKey": false,
          "notNull": true,
          "autoincrement": false
        },
        "ai_type": {
          "name": "ai_type",
          "type": "text",
          "primaryKey": false,
          "notNull": true,
          "autoincrement": false
        },
        "input": {
          "name": "input",
          "type": "text",
          "primaryKey": false,
          "notNull": true,
          "autoincrement": false
        },
        "output": {
          "name": "output",
          "type": "text",
          "primaryKey": false,
          "notNull": true,
          "autoincrement": false
        },
        "created_at": {
          "name": "created_at",
          "type": "integer",
          "primaryKey": false,
          "notNull": true,
          "autoincrement": false
        }
      },
      "indexes": {
        "analysis_history_project_id_idx": {
          "name": "analysis_history_project_id_idx",
          "columns": [
            "project_id"
          ],
          "isUnique": false
        }
      },
      "foreignKeys": {
        "analysis_history_project_id_project_project_id_fk": {
          "name": "analysis_history_project_id_project_project_id_fk",
          "tableFrom": "analysis_history",
          "tableTo": "project",
          "columnsFrom": [
            "project_id"
          ],
          "columnsTo": [
            "project_id"
          ],
          "onDelete": "cascade",
          "onUpdate": "no action"
        }
      },
      "compositePrimaryKeys": {},
      "uniqueConstraints": {}
    },
    "api_usage": {
      "name": "api_usage",
      "columns": {
        "id": {
          "name": "id",
          "type": "integer",
          "primaryKey": true,
          "notNull": true,
          "autoincrement": true
        },
        "project_id": {
          "name": "project_id",
          "type": "text",
          "primaryKey": false,
          "notNull": true,
          "autoincrement": false
        },
        "used_at": {
          "name": "used_at",
          "type": "integer",
          "primaryKey": false,
          "notNull": true,
          "autoincrement": false
        }
      },
      "indexes": {
        "api_usage_project_id_idx": {
          "name": "api_usage_project_id_idx",
          "columns": [
            "project_id"
          ],
          "isUnique": false
        },
        "api_usage_used_at_idx": {
          "name": "api_usage_used_at_idx",
          "columns": [
            "used_at"
          ],
          "isUnique": false
        }
      },
      "foreignKeys": {
        "api_usage_project_id_project_project_id_fk": {
          "name": "api_usage_project_id_project_project_id_fk",
          "tableFrom": "api_usage",
          "tableTo": "project",
          "columnsFrom": [
            "project_id"
          ],
          "columnsTo": [
            "project_id"
          ],
          "onDelete": "cascade",
          "onUpdate": "no action"
        }
      },
      "compositePrimaryKeys": {},
      "uniqueConstraints": {}
    },
    "application_settings": {
      "name": "application_settings",
      "columns": {
        "id": {
          "name": "id",
          "type": "integer",
          "primaryKey": true,
          "notNull": true,
          "autoincrement": true
        },
        "key": {
          "name": "key",
          "type": "text",
          "primaryKey": false,
          "notNull": true,
          "autoincrement": false
        },
        "value": {
          "name": "value",
          "type": "text",
          "primaryKey": false,
          "notNull": true,
          "autoincrement": false
        }
      },
      "indexes": {
        "application_settings_key_unique": {
          "name": "application_settings_key_unique",
          "columns": [
            "key"
          ],
          "isUnique": true
        },
        "application_settings_key_idx": {
          "name": "application_settings_key_idx",
          "columns": [
            "key"
          ],
          "isUnique": true
        }
      },
      "foreignKeys": {},
      "compositePrimaryKeys": {},
      "uniqueConstraints": {}
    },
    "auth": {
      "name": "auth",
      "columns": {
        "id": {
          "name": "id",
          "type": "text",
          "primaryKey": true,
          "notNull": true,
          "autoincrement": false
        },
        "password": {
          "name": "password",
          "type": "text",
          "primaryKey": false,
          "notNull": true,
          "autoincrement": false
        }
      },
      "indexes": {},
      "foreignKeys": {},
      "compositePrimaryKeys": {},
      "uniqueConstraints": {}
    },
    "help": {
      "name": "help",
      "columns": {
        "id": {
          "name": "id",
          "type": "integer",
          "primaryKey": true,
          "notNull": true,
          "autoincrement": true
        },
        "ai_type": {
          "name": "ai_type",
          "type": "text",
          "primaryKey": false,
          "notNull": true,
          "autoincrement": false
        },
        "text": {
          "name": "text",
          "type": "text",
          "primaryKey": false,
          "notNull": true,
          "autoincrement": false
        }
      },
      "indexes": {
        "help_ai_type_unique": {
          "name": "help_ai_type_unique",
          "columns": [
            "ai_type"
          ],
          "isUnique": true
        },
        "help_ai_type_idx": {
          "name": "help_ai_type_idx",
          "columns": [
            "ai_type"
          ],
          "isUnique": true
        }
      },
      "foreignKeys": {},
      "compositePrimaryKeys": {},
      "uniqueConstraints": {}
    },
    "instruction_guide": {
      "name": "instruction_guide",
      "columns": {
        "id": {
          "name": "id",
          "type": "integer",
          "primaryKey": true,
          "notNull": true,
          "autoincrement": true
        },
        "form_name": {
          "name": "form_name",
          "type": "text",
          "primaryKey": false,
          "notNull": true,
          "autoincrement": false
        },
        "text": {
          "name": "text",
          "type": "text",
          "primaryKey": false,
          "notNull": true,
          "autoincrement": false
        }
      },
      "indexes": {
        "instruction_guide_form_name_unique": {
          "name": "instruction_guide_form_name_unique",
          "columns": [
            "form_name"
          ],
          "isUnique": true
        }
      },
      "foreignKeys": {},
      "compositePrimaryKeys": {},
      "uniqueConstraints": {}
    },
    "project_info": {
      "name": "project_info",
      "columns": {
        "id": {
          "name": "id",
          "type": "integer",
          "primaryKey": true,
          "notNull": true,
          "autoincrement": true
        },
        "project_id": {
          "name": "project_id",
          "type": "text",
          "primaryKey": false,
          "notNull": true,
          "autoincrement": false
        },
        "business_type": {
          "name": "business_type",
          "type": "text",
          "primaryKey": false,
          "notNull": false,
          "autoincrement": false
        },
        "address": {
          "name": "address",
          "type": "text",
          "primaryKey": false,
          "notNull": false,
          "autoincrement": false
        },
        "nearest_station": {
          "name": "nearest_station",
          "type": "text",
          "primaryKey": false,
          "notNull": false,
          "autoincrement": false
        },
        "concept": {
          "name": "concept",
          "type": "text",
          "primaryKey": false,
          "notNull": false,
          "autoincrement": false
        },
        "strength": {
          "name": "strength",
          "type": "text",
          "primaryKey": false,
          "notNull": false,
          "autoincrement": false
        },
        "target_age": {
          "name": "target_age",
          "type": "text",
          "primaryKey": false,
          "notNull": false,
          "autoincrement": false
        },
        "targetGender": {
          "name": "targetGender",
          "type": "text",
          "primaryKey": false,
          "notNull": false,
          "autoincrement": false
        },
        "target_area": {
          "name": "target_area",
          "type": "text",
          "primaryKey": false,
          "notNull": false,
          "autoincrement": false
        },
        "target_attribute": {
          "name": "target_attribute",
          "type": "text",
          "primaryKey": false,
          "notNull": false,
          "autoincrement": false
        },
        "target_concern": {
          "name": "target_concern",
          "type": "text",
          "primaryKey": false,
          "notNull": false,
          "autoincrement": false
        },
        "existing_customer_analysis": {
          "name": "existing_customer_analysis",
          "type": "text",
          "primaryKey": false,
          "notNull": false,
          "autoincrement": false
        }
      },
      "indexes": {
        "project_info_project_id_idx": {
          "name": "project_info_project_id_idx",
          "columns": [
            "project_id"
          ],
          "isUnique": true
        }
      },
      "foreignKeys": {
        "project_info_project_id_project_project_id_fk": {
          "name": "project_info_project_id_project_project_id_fk",
          "tableFrom": "project_info",
          "tableTo": "project",
          "columnsFrom": [
            "project_id"
          ],
          "columnsTo": [
            "project_id"
          ],
          "onDelete": "cascade",
          "onUpdate": "no action"
        }
      },
      "compositePrimaryKeys": {},
      "uniqueConstraints": {}
    },
    "project": {
      "name": "project",
      "columns": {
        "id": {
          "name": "id",
          "type": "integer",
          "primaryKey": true,
          "notNull": true,
          "autoincrement": true
        },
        "name": {
          "name": "name",
          "type": "text",
          "primaryKey": false,
          "notNull": true,
          "autoincrement": false
        },
        "auth_id": {
          "name": "auth_id",
          "type": "text",
          "primaryKey": false,
          "notNull": false,
          "autoincrement": false
        },
        "manager_name": {
          "name": "manager_name",
          "type": "text",
          "primaryKey": false,
          "notNull": true,
          "autoincrement": false
        },
        "owner_name": {
          "name": "owner_name",
          "type": "text",
          "primaryKey": false,
          "notNull": true,
          "autoincrement": false
        },
        "project_id": {
          "name": "project_id",
          "type": "text",
          "primaryKey": false,
          "notNull": true,
          "autoincrement": false
        },
        "project_pass": {
          "name": "project_pass",
          "type": "text",
          "primaryKey": false,
          "notNull": true,
          "autoincrement": false
        },
        "api_usage_limit": {
          "name": "api_usage_limit",
          "type": "integer",
          "primaryKey": false,
          "notNull": true,
          "autoincrement": false
        }
      },
      "indexes": {
        "project_project_id_unique": {
          "name": "project_project_id_unique",
          "columns": [
            "project_id"
          ],
          "isUnique": true
        },
        "project_project_id_idx": {
          "name": "project_project_id_idx",
          "columns": [
            "project_id"
          ],
          "isUnique": true
        }
      },
      "foreignKeys": {
        "project_auth_id_auth_id_fk": {
          "name": "project_auth_id_auth_id_fk",
          "tableFrom": "project",
          "tableTo": "auth",
          "columnsFrom": [
            "auth_id"
          ],
          "columnsTo": [
            "id"
          ],
          "onDelete": "no action",
          "onUpdate": "no action"
        }
      },
      "compositePrimaryKeys": {},
      "uniqueConstraints": {}
    },
    "prompt": {
      "name": "prompt",
      "columns": {
        "id": {
          "name": "id",
          "type": "integer",
          "primaryKey": true,
          "notNull": true,
          "autoincrement": true
        },
        "ai_type": {
          "name": "ai_type",
          "type": "text",
          "primaryKey": false,
          "notNull": true,
          "autoincrement": false
        },
        "system": {
          "name": "system",
          "type": "text",
          "primaryKey": false,
          "notNull": true,
          "autoincrement": false
        },
        "user": {
          "name": "user",
          "type": "text",
          "primaryKey": false,
          "notNull": true,
          "autoincrement": false
        }
      },
      "indexes": {
        "prompt_ai_type_unique": {
          "name": "prompt_ai_type_unique",
          "columns": [
            "ai_type"
          ],
          "isUnique": true
        },
        "prompt_ai_type_idx": {
          "name": "prompt_ai_type_idx",
          "columns": [
            "ai_type"
          ],
          "isUnique": false
        }
      },
      "foreignKeys": {},
      "compositePrimaryKeys": {},
      "uniqueConstraints": {}
    },
    "session": {
      "name": "session",
      "columns": {
        "id": {
          "name": "id",
          "type": "text",
          "primaryKey": true,
          "notNull": true,
          "autoincrement": false
        },
        "project_id": {
          "name": "project_id",
          "type": "text",
          "primaryKey": false,
          "notNull": true,
          "autoincrement": false
        },
        "expires_at": {
          "name": "expires_at",
          "type": "integer",
          "primaryKey": false,
          "notNull": true,
          "autoincrement": false
        }
      },
      "indexes": {
        "session_id_idx": {
          "name": "session_id_idx",
          "columns": [
            "id"
          ],
          "isUnique": true
        }
      },
      "foreignKeys": {
        "session_project_id_project_project_id_fk": {
          "name": "session_project_id_project_project_id_fk",
          "tableFrom": "session",
          "tableTo": "project",
          "columnsFrom": [
            "project_id"
          ],
          "columnsTo": [
            "project_id"
          ],
          "onDelete": "cascade",
          "onUpdate": "no action"
        }
      },
      "compositePrimaryKeys": {},
      "uniqueConstraints": {}
    }
  },
  "enums": {},
  "_meta": {
    "schemas": {},
    "tables": {},
    "columns": {}
  },
  "internal": {
    "indexes": {}
  }
}